Topsis/__init__.py
Topsis/__main__.py
Topsis_BhaveshSareen_101917085-1.0.0.dist-info/METADATA
Topsis_BhaveshSareen_101917085-1.0.0.dist-info/WHEEL
Topsis_BhaveshSareen_101917085-1.0.0.dist-info/top_level.txt
Topsis_BhaveshSareen_101917085-1.0.0.dist-info/RECORD
