Metadata-Version: 2.1
Name: Topsis-BhaveshSareen-101917085
Version: 1.0.0
Summary: Assignment of Bhavesh Sareen
Home-page: 
Author: Bhavesh Sareen
Author-email: sareenbahvesh26@gmail.com
License: MIT
Platform: UNKNOWN
Classifier: License :: OSI Approved :: MIT License
Classifier: Programming Language :: Python :: 3.6
Classifier: Programming Language :: Python :: 3.7
Classifier: Programming Language :: Python :: 3.8
